atoolkitdpt/__init__.py
atoolkitdpt/dpt/__init__.py
atoolkitdpt/dpt/base_model.py
atoolkitdpt/dpt/blocks.py
atoolkitdpt/dpt/midas_net.py
atoolkitdpt/dpt/models.py
atoolkitdpt/dpt/transforms.py
atoolkitdpt/dpt/vit.py
atoolkitdpt/midas/__init__.py
atoolkitdpt/midas/base_model.py
atoolkitdpt/midas/blocks.py
atoolkitdpt/midas/dpt_depth.py
atoolkitdpt/midas/midas_net.py
atoolkitdpt/midas/midas_net_custom.py
atoolkitdpt/midas/model_loader.py
atoolkitdpt/midas/transforms.py
atoolkitdpt/midas/utils.py
atoolkitdpt/midas/backbones/__init__.py
atoolkitdpt/midas/backbones/beit.py
atoolkitdpt/midas/backbones/levit.py
atoolkitdpt/midas/backbones/next_vit.py
atoolkitdpt/midas/backbones/swin.py
atoolkitdpt/midas/backbones/swin2.py
atoolkitdpt/midas/backbones/swin_common.py
atoolkitdpt/midas/backbones/utils.py
atoolkitdpt/midas/backbones/vit.py
atoolkitdpt/util/__init__.py
atoolkitdpt/util/io.py
atoolkitdpt/util/misc.py
atoolkitdpt/util/pallete.py
atoolkitdpt-0.0.2.dist-info/LICENSE
atoolkitdpt-0.0.2.dist-info/METADATA
atoolkitdpt-0.0.2.dist-info/WHEEL
atoolkitdpt-0.0.2.dist-info/top_level.txt
atoolkitdpt-0.0.2.dist-info/RECORD
