Metadata-Version: 2.1
Name: atoolkitdpt
Version: 0.0.2
Summary: Midas and Dense Prediction Transformers modules for Ambrosinus-Toolkit
Home-page: https://github.com/lucianoambrosini/AToolkitDpt
Author: Luciano Ambrosini
Author-email: luciano.ambrosini@outlook.com
Classifier: Programming Language :: Python :: 3
Classifier: License :: OSI Approved :: MIT License
Classifier: Operating System :: OS Independent
Requires-Python: >=3.7
License-File: LICENSE
